crispy_forms/__init__.py
crispy_forms/base.py
crispy_forms/bootstrap.py
crispy_forms/compatibility.py
crispy_forms/exceptions.py
crispy_forms/helper.py
crispy_forms/layout.py
crispy_forms/layout_slice.py
crispy_forms/models.py
crispy_forms/utils.py
crispy_forms/templates/bootstrap/accordion-group.html
crispy_forms/templates/bootstrap/accordion.html
crispy_forms/templates/bootstrap/betterform.html
crispy_forms/templates/bootstrap/display_form.html
crispy_forms/templates/bootstrap/errors.html
crispy_forms/templates/bootstrap/errors_formset.html
crispy_forms/templates/bootstrap/field.html
crispy_forms/templates/bootstrap/table_inline_formset.html
crispy_forms/templates/bootstrap/uni_form.html
crispy_forms/templates/bootstrap/uni_formset.html
crispy_forms/templates/bootstrap/whole_uni_form.html
crispy_forms/templates/bootstrap/whole_uni_formset.html
crispy_forms/templates/bootstrap/layout/alert.html
crispy_forms/templates/bootstrap/layout/baseinput.html
crispy_forms/templates/bootstrap/layout/button.html
crispy_forms/templates/bootstrap/layout/checkboxselectmultiple.html
crispy_forms/templates/bootstrap/layout/checkboxselectmultiple_inline.html
crispy_forms/templates/bootstrap/layout/div.html
crispy_forms/templates/bootstrap/layout/field_errors.html
crispy_forms/templates/bootstrap/layout/field_errors_block.html
crispy_forms/templates/bootstrap/layout/field_with_buttons.html
crispy_forms/templates/bootstrap/layout/fieldset.html
crispy_forms/templates/bootstrap/layout/formactions.html
crispy_forms/templates/bootstrap/layout/help_text.html
crispy_forms/templates/bootstrap/layout/help_text_and_errors.html
crispy_forms/templates/bootstrap/layout/multifield.html
crispy_forms/templates/bootstrap/layout/prepended_appended_text.html
crispy_forms/templates/bootstrap/layout/radioselect.html
crispy_forms/templates/bootstrap/layout/radioselect_inline.html
crispy_forms/templates/bootstrap/layout/tab-link.html
django_crispy_forms_ng-2.0.0.dist-info/DESCRIPTION.rst
django_crispy_forms_ng-2.0.0.dist-info/METADATA
django_crispy_forms_ng-2.0.0.dist-info/RECORD
django_crispy_forms_ng-2.0.0.dist-info/WHEEL
django_crispy_forms_ng-2.0.0.dist-info/metadata.json
django_crispy_forms_ng-2.0.0.dist-info/top_level.txt
