Metadata-Version: 1.1
Name: django-crispy-forms-ng
Version: 2.0.0
Summary: Best way to have Django DRY forms of the next generation.
Home-page: http://github.com/maraujop/django-crispy-forms
Author: Tzu-ping Chung and Miguel Araujo
Author-email: uranusjr@gmail.com
License: MIT
Keywords: forms,django,crispy,DRY
Platform: UNKNOWN
Classifier: Development Status :: 5 - Production/Stable
Classifier: Environment :: Web Environment
Classifier: Framework :: Django
Classifier: License :: OSI Approved :: BSD License
Classifier: Operating System :: OS Independent
Classifier: Programming Language :: JavaScript
Classifier: Programming Language :: Python :: 2.6
Classifier: Programming Language :: Python :: 2.7
Classifier: Programming Language :: Python :: 3.3
Classifier: Programming Language :: Python :: 3.4
Classifier: Topic :: Internet :: WWW/HTTP
Classifier: Topic :: Internet :: WWW/HTTP :: Dynamic Content
Classifier: Topic :: Software Development :: Libraries :: Python Modules
